app/__init__.py
app/__main__.py
app/main.py
app/server.py
mseep_typecast_api_mcp_server-0.1.2.dist-info/METADATA
mseep_typecast_api_mcp_server-0.1.2.dist-info/WHEEL
mseep_typecast_api_mcp_server-0.1.2.dist-info/entry_points.txt
mseep_typecast_api_mcp_server-0.1.2.dist-info/RECORD
